delaunay/__init__.py
delaunay/delaunay.py
delaunay/quadedge/__init__.py
delaunay/quadedge/edge.py
delaunay/quadedge/mesh.py
delaunay/quadedge/point.py
delaunay/quadedge/primitives.py
delaunay-1.0.5.dist-info/LICENSE
delaunay-1.0.5.dist-info/METADATA
delaunay-1.0.5.dist-info/WHEEL
delaunay-1.0.5.dist-info/top_level.txt
delaunay-1.0.5.dist-info/RECORD
