Metadata-Version: 2.1
Name: delaunay
Version: 1.0.5
Summary: a lightweight 2d delaunay triangulator based on algorithm by Guibas & Stolfi
Author: mkirc
Author-email: m.p.kirchner@gmx.de
Project-URL: Source Files, https://github.com/mkirc/delaunay
Classifier: Programming Language :: Python :: 3
Classifier: License :: OSI Approved :: MIT License
Classifier: Operating System :: OS Independent
Requires-Python: >=3.6
License-File: LICENSE
